Metadata-Version: 1.0
Name: gibiga-distributions
Version: 0.0.2
Summary: Gaussian distributions
Home-page: UNKNOWN
Author: Greg Izzo
Author-email: greg.izzo@gmail.com
License: UNKNOWN
Platform: UNKNOWN
